examples/__init__.py
examples/openai_basic_usage.py
optune/__init__.py
optune/openai/__init__.py
optune/openai/client.py
optune/openai/optune_chat.py
optune/openai/optune_completions.py
optune/optune/__init__.py
optune/optune/inference.py
optune/optune/lm_response_types.py
optune/optune/tracing.py
optune-0.1.1.dist-info/METADATA
optune-0.1.1.dist-info/WHEEL
optune-0.1.1.dist-info/top_level.txt
optune-0.1.1.dist-info/RECORD
