Metadata-Version: 2.4
Name: optune
Version: 0.1.1
Summary: optune.ai python sdk
Home-page: https://optune.ai/
Author: optune.ai team
Author-email: support@optune.ai
Classifier: Programming Language :: Python :: 3
Classifier: Operating System :: OS Independent
Requires-Dist: requests
Requires-Dist: openai
Requires-Dist: pydantic
Provides-Extra: dev
Requires-Dist: pytest; extra == "dev"
Requires-Dist: pandas; extra == "dev"
Dynamic: author
Dynamic: author-email
Dynamic: classifier
Dynamic: description
Dynamic: description-content-type
Dynamic: home-page
Dynamic: provides-extra
Dynamic: requires-dist
Dynamic: summary
